main.py
my_password_mcp-0.1.0.dist-info/METADATA
my_password_mcp-0.1.0.dist-info/WHEEL
my_password_mcp-0.1.0.dist-info/entry_points.txt
my_password_mcp-0.1.0.dist-info/RECORD
