Metadata-Version: 2.4
Name: my-password-mcp
Version: 0.1.0
Summary: My first MCP tool
Requires-Dist: fastmcp
